{"width":640,"height":480,"valid":true,"rotate":0,"step_1":{"toolName":"rectTool","result":[{"x":195.99622497318333,"y":6.97315587638168,"width":246.82885777816617,"height":84.13264155199629,"attribute":"O2","valid":true,"id":"h01IyCNZ","sourceID":"","textAttribute":"","order":6},{"x":310.85043988269786,"y":128.7976539589442,"width":118.86514220895411,"height":115.29859703579291,"attribute":"O1","valid":true,"id":"lTxWjIPh","sourceID":"","textAttribute":"","order":5},{"x":384.7507331378299,"y":121.05571847507322,"width":253.84164222873875,"height":152.02346041055705,"attribute":"left-hand","valid":true,"id":"EL051h8b","sourceID":"","textAttribute":"","order":3},{"x":192.22790113112686,"y":0,"width":283.48786697173796,"height":95.9642016969206,"attribute":"R-O","valid":true,"id":"rjs16ocm","sourceID":"","textAttribute":"","order":2},{"x":324.2445296638843,"y":0,"width":149.18655538010373,"height":81.67471238438975,"attribute":"right-hand","valid":true,"id":"TeIVRFpn","sourceID":"","textAttribute":"","order":4},{"x":316.3114489197438,"y":129.5014662756598,"width":315.93416721527325,"height":125.98240469208206,"attribute":"L-O","valid":true,"id":"VyA22bvJ","sourceID":"","textAttribute":"","order":1}]}}